__init__.py
demystify/__init__.py
demystify/config.cfg
demystify/demystify.py
demystify/denylist_template.py
demystify/i18n/README.md
demystify/i18n/__init__.py
demystify/i18n/internationalstrings.py
demystify/libs/AnalysisQueriesClass.py
demystify/libs/AnalysisResultsClass.py
demystify/libs/DemystifyAnalysisClass.py
demystify/libs/DenylistQueriesClass.py
demystify/libs/HandleDenylistClass.py
demystify/libs/IdentifyDatabase.py
demystify/libs/RoguesQueriesClass.py
demystify/libs/__init__.py
demystify/libs/version.py
demystify/libs/outputhandlers/__init__.py
demystify/libs/outputhandlers/htmloutputclass.py
demystify/libs/outputhandlers/roguesgalleryoutputclass.py
demystify/libs/outputhandlers/textoutputclass.py
demystify/pathlesstaken/__init__.py
demystify/pathlesstaken/pathlesstaken.py
demystify/pathlesstaken/setup.py
demystify/pathlesstaken/src/__init__.py
demystify/pathlesstaken/src/pathlesstaken/__init__.py
demystify/pathlesstaken/src/pathlesstaken/internationalstrings.py
demystify/pathlesstaken/src/pathlesstaken/names.py
demystify/pathlesstaken/src/pathlesstaken/pathlesstaken.py
demystify/pathlesstaken/src/pathlesstaken/ucd.py
demystify/pathlesstaken/src/pathlesstaken/version.py
demystify/pathlesstaken/src/pathlesstaken/i18n/__init__.py
demystify/pathlesstaken/src/pathlesstaken/i18n/internationalstrings.py
demystify/sqlitefid/__init__.py
demystify/sqlitefid/setup.py
demystify/sqlitefid/sqlitefid.py
demystify/sqlitefid/src/__init__.py
demystify/sqlitefid/src/sqlitefid/__init__.py
demystify/sqlitefid/src/sqlitefid/sqlitefid.py
demystify/sqlitefid/src/sqlitefid/libs/CSVHandlerClass.py
demystify/sqlitefid/src/sqlitefid/libs/DROIDLoaderClass.py
demystify/sqlitefid/src/sqlitefid/libs/FidoLoaderClass.py
demystify/sqlitefid/src/sqlitefid/libs/GenerateBaselineDBClass.py
demystify/sqlitefid/src/sqlitefid/libs/IdentifyExportClass.py
demystify/sqlitefid/src/sqlitefid/libs/PyDateHandler.py
demystify/sqlitefid/src/sqlitefid/libs/SFHandlerClass.py
demystify_digipres-2.0.0.dist-info/LICENSE.txt
demystify_digipres-2.0.0.dist-info/METADATA
demystify_digipres-2.0.0.dist-info/WHEEL
demystify_digipres-2.0.0.dist-info/entry_points.txt
demystify_digipres-2.0.0.dist-info/top_level.txt
demystify_digipres-2.0.0.dist-info/RECORD
