Metadata-Version: 2.1
Name: demystify-digipres
Version: 2.0.0
Summary: engine for the analysis of DROID and Siegfried file format reports
Author: Ross Spencer
License: Copyright (c) 2013 Ross Spencer
Project-URL: Bug Reports, https://github.com/exponential-decay/demystify/issues/
Project-URL: Source, https://github.com/exponential-decay/demystify
Requires-Python: >=3.8
License-File: LICENSE.txt
